ketama.cpython-36m-x86_64-linux-gnu.so
ketama-0.1.1.dist-info/WHEEL
ketama-0.1.1.dist-info/top_level.txt
ketama-0.1.1.dist-info/METADATA
ketama-0.1.1.dist-info/RECORD
